fasttttsandbox/__init__.py
fasttttsandbox-0.0.4.dist-info/METADATA
fasttttsandbox-0.0.4.dist-info/WHEEL
fasttttsandbox-0.0.4.dist-info/licenses/LICENSE
fasttttsandbox-0.0.4.dist-info/RECORD
