Metadata-Version: 2.4
Name: fasttttsandbox
Version: 0.0.4
Summary: An implementation of tic tac toe where players each make 'n' moves per turn
Project-URL: Homepage, https://github.com/Timothy-Flavin/FastTTTSandbox/
Project-URL: Bug Tracker, https://github.com/Timothy-Flavin/FastTTTSandbox/issues
Author-email: Timothy Flavin <timothy.c.flavin@gmail.com>
License-File: LICENSE
Classifier: License :: OSI Approved :: GNU General Public License v3 (GPLv3)
Classifier: Operating System :: OS Independent
Classifier: Programming Language :: Python :: 3
Requires-Python: >=3.7
